ansible_api/__init__.py
ansible_api/callback.py
ansible_api/config.py
ansible_api/controller.py
ansible_api/realtimemsg.py
ansible_api/report.py
ansible_api/server.py
ansible_api/tool.py
ansible_api-0.5.1.data/scripts/ansible-api
ansible_api-0.5.1.dist-info/LICENSE
ansible_api-0.5.1.dist-info/METADATA
ansible_api-0.5.1.dist-info/WHEEL
ansible_api-0.5.1.dist-info/top_level.txt
ansible_api-0.5.1.dist-info/RECORD
