Metadata-Version: 2.1
Name: ansible-api
Version: 0.5.1
Summary: A restful HTTP API for ansible
Home-page: https://github.com/lfbear/ansible-api
Author: lfbear
Author-email: lfbear@gmail.com
License: GPLv3
Project-URL: Bug Reports, https://github.com/lfbear/ansible-api/issues
Project-URL: Source, https://github.com/lfbear/ansible-api
Platform: UNKNOWN
Classifier: Development Status :: 5 - Production/Stable
Classifier: Programming Language :: Python :: 3.7
Classifier: Operating System :: OS Independent
Classifier: Topic :: System :: Systems Administration
Classifier: Topic :: Utilities
Classifier: License :: OSI Approved :: GNU General Public License v3 (GPLv3)
Requires-Python: >=3.7
License-File: LICENSE
Requires-Dist: sanic (>=0.8.0)
Requires-Dist: ansible (>=2.6.0)
Requires-Dist: ansible-runner (>=1.2.0)
